README.md
setup.py
requests_spider/__init__.py
requests_spider/const.py
requests_spider/field.py
requests_spider/logger.py
requests_spider/model.py
requests_spider/request.py
requests_spider/response.py
requests_spider/rule.py
requests_spider/spider.py
requests_spider/squeue.py
requests_spider.egg-info/PKG-INFO
requests_spider.egg-info/SOURCES.txt
requests_spider.egg-info/dependency_links.txt
requests_spider.egg-info/not-zip-safe
requests_spider.egg-info/requires.txt
requests_spider.egg-info/top_level.txt