Metadata-Version: 1.2
Name: requests-spider
Version: 0.0.8
Summary: Web crawling framework like flask.
Home-page: https://github.com/Tooooomy/requests_spider
Author: Tommy
Author-email: tooooommy@163.com
License: MIT
Platform: all
Classifier: License :: OSI Approved :: MIT License
Classifier: Programming Language :: Python
Classifier: Programming Language :: Python :: 3.6
Classifier: Programming Language :: Python :: Implementation :: CPython
Classifier: Programming Language :: Python :: Implementation :: PyPy
Requires-Python: >=3.6.0
